invoice_vision/__init__.py
invoice_vision-0.0.1.dist-info/LICENSE
invoice_vision-0.0.1.dist-info/WHEEL
invoice_vision-0.0.1.dist-info/METADATA
invoice_vision-0.0.1.dist-info/RECORD
