Metadata-Version: 2.1
Name: invoice-vision
Version: 0.0.1
Summary: Application to extract structured information from invoice images
Home-page: https://github.com/dcooper01/invoice-vision
License: MIT
Author: Daniel
Author-email: dcooper01sp@protonmail.com
Maintainer: Daniel
Maintainer-email: dcooper01sp@protonmail.com
Requires-Python: >=3.8,<4.0
Classifier: License :: OSI Approved :: MIT License
Classifier: Programming Language :: Python :: 3
Classifier: Programming Language :: Python :: 3.8
Project-URL: Repository, https://github.com/dcooper01/invoice-vision
